test/__init__.py
test/test_zingl.py
zinglplotter/__init__.py
zinglplotter/zinglplotter.py
zinglplotter-1.0.0.dist-info/LICENSE
zinglplotter-1.0.0.dist-info/METADATA
zinglplotter-1.0.0.dist-info/WHEEL
zinglplotter-1.0.0.dist-info/top_level.txt
zinglplotter-1.0.0.dist-info/zip-safe
zinglplotter-1.0.0.dist-info/RECORD
