Metadata-Version: 2.1
Name: zinglplotter
Version: 1.0.0
Summary: Zingl Path Plotting
Home-page: https://github.com/meerk40t/zinglplotter
Author: Tatarize
Author-email: tatarize@gmail.com
License: MIT
Keywords: plotting,raster
Classifier: Development Status :: 5 - Production/Stable
Classifier: Intended Audience :: Developers
Classifier: License :: OSI Approved :: MIT License
Classifier: Operating System :: OS Independent
Classifier: Programming Language :: Python
Classifier: Programming Language :: Python :: 3.5
Classifier: Programming Language :: Python :: 3.6
Classifier: Programming Language :: Python :: 3.7
Classifier: Programming Language :: Python :: Implementation :: PyPy
Classifier: Topic :: Software Development :: Libraries :: Python Modules
License-File: LICENSE
